drafthorse/__init__.py
drafthorse/pdf.py
drafthorse/utils.py
drafthorse/xmp_schema.py
drafthorse/models/__init__.py
drafthorse/models/accounting.py
drafthorse/models/container.py
drafthorse/models/delivery.py
drafthorse/models/document.py
drafthorse/models/elements.py
drafthorse/models/fields.py
drafthorse/models/note.py
drafthorse/models/party.py
drafthorse/models/payment.py
drafthorse/models/product.py
drafthorse/models/references.py
drafthorse/models/trade.py
drafthorse/models/tradelines.py
drafthorse/schema/Factur-X_1.0.07_BASIC.xsd
drafthorse/schema/Factur-X_1.0.07_BASICWL.xsd
drafthorse/schema/Factur-X_1.0.07_BASICWL_codedb.xml
drafthorse/schema/Factur-X_1.0.07_BASICWL_urn_un_unece_uncefact_data_standard_QualifiedDataType_100.xsd
drafthorse/schema/Factur-X_1.0.07_BASICWL_urn_un_unece_uncefact_data_standard_ReusableAggregateBusinessInformationEntity_100.xsd
drafthorse/schema/Factur-X_1.0.07_BASICWL_urn_un_unece_uncefact_data_standard_UnqualifiedDataType_100.xsd
drafthorse/schema/Factur-X_1.0.07_BASIC_codedb.xml
drafthorse/schema/Factur-X_1.0.07_BASIC_urn_un_unece_uncefact_data_standard_QualifiedDataType_100.xsd
drafthorse/schema/Factur-X_1.0.07_BASIC_urn_un_unece_uncefact_data_standard_ReusableAggregateBusinessInformationEntity_100.xsd
drafthorse/schema/Factur-X_1.0.07_BASIC_urn_un_unece_uncefact_data_standard_UnqualifiedDataType_100.xsd
drafthorse/schema/Factur-X_1.0.07_EN16931.xsd
drafthorse/schema/Factur-X_1.0.07_EN16931_codedb.xml
drafthorse/schema/Factur-X_1.0.07_EN16931_urn_un_unece_uncefact_data_standard_QualifiedDataType_100.xsd
drafthorse/schema/Factur-X_1.0.07_EN16931_urn_un_unece_uncefact_data_standard_ReusableAggregateBusinessInformationEntity_100.xsd
drafthorse/schema/Factur-X_1.0.07_EN16931_urn_un_unece_uncefact_data_standard_UnqualifiedDataType_100.xsd
drafthorse/schema/Factur-X_1.0.07_EXTENDED.xsd
drafthorse/schema/Factur-X_1.0.07_EXTENDED_codedb.xml
drafthorse-2025.2.0.dist-info/licenses/LICENSE
drafthorse-2025.2.0.dist-info/METADATA
drafthorse-2025.2.0.dist-info/WHEEL
drafthorse-2025.2.0.dist-info/top_level.txt
drafthorse-2025.2.0.dist-info/RECORD
