Metadata-Version: 2.4
Name: drafthorse
Version: 2025.2.0
Summary: Python ZUGFeRD XML implementation
Home-page: https://github.com/pretix/python-drafthorse
Author: Raphael Michel
Author-email: michel@rami.io
License: Apache License
Keywords: xml banking sepa
Classifier: Intended Audience :: Developers
Classifier: Intended Audience :: Other Audience
Classifier: License :: OSI Approved :: Apache Software License
Classifier: Programming Language :: Python :: 3.7
Classifier: Programming Language :: Python :: 3.8
Classifier: Programming Language :: Python :: 3.9
Classifier: Programming Language :: Python :: 3.10
License-File: LICENSE
Requires-Dist: lxml
Requires-Dist: pypdf
Dynamic: author
Dynamic: author-email
Dynamic: classifier
Dynamic: description
Dynamic: home-page
Dynamic: keywords
Dynamic: license
Dynamic: license-file
Dynamic: requires-dist
Dynamic: summary
